miniipe/__init__.py
miniipe-0.4.0.dist-info/LICENSE
miniipe-0.4.0.dist-info/METADATA
miniipe-0.4.0.dist-info/WHEEL
miniipe-0.4.0.dist-info/top_level.txt
miniipe-0.4.0.dist-info/RECORD
