Metadata-Version: 2.1
Name: miniipe
Version: 0.4.0
Summary: An easy, no-dependencies package for writing IPE files from Python.
Home-page: https://github.com/tcvdijk/mini-ipe
Author: Thomas van Dijk
Author-email: tvdmaps@gmail.com
License: UNKNOWN
Platform: UNKNOWN
Classifier: Programming Language :: Python :: 3
Classifier: License :: OSI Approved :: MIT License
Classifier: Operating System :: OS Independent
Requires-Python: >=3.6
